nem_bidding_dashboard/__init__.py
nem_bidding_dashboard/assets/base_styles.css
nem_bidding_dashboard/assets/fonts.css
nem_bidding_dashboard/assets/template_styles.css
nem_bidding_dashboard/build_postgres_db.py
nem_bidding_dashboard/create_plots.py
nem_bidding_dashboard/defaults.py
nem_bidding_dashboard/fetch_and_preprocess.py
nem_bidding_dashboard/fetch_data.py
nem_bidding_dashboard/index_creation.py
nem_bidding_dashboard/input_validation.py
nem_bidding_dashboard/layout_template.py
nem_bidding_dashboard/plot_bids.py
nem_bidding_dashboard/populate_postgres_db.py
nem_bidding_dashboard/populate_supabase_db.py
nem_bidding_dashboard/postgres_helpers.py
nem_bidding_dashboard/preprocessing.py
nem_bidding_dashboard/query_cached_data.py
nem_bidding_dashboard/query_functions_for_dashboard.py
nem_bidding_dashboard/query_postgres_db.py
nem_bidding_dashboard/query_supabase_db.py
nem_bidding_dashboard/run_dashboard.py
nem_bidding_dashboard-1.0.8.dist-info/LICENSE
nem_bidding_dashboard-1.0.8.dist-info/WHEEL
nem_bidding_dashboard-1.0.8.dist-info/METADATA
nem_bidding_dashboard-1.0.8.dist-info/RECORD
