Metadata-Version: 2.1
Name: nem-bidding-dashboard
Version: 1.0.8
Summary: A dashboard for visualising bidding data from the Australian National Electricity Market
License: BSD 3-clause
Author: Patrick Chambers
Requires-Python: >=3.8,<3.11
Classifier: License :: Other/Proprietary License
Classifier: Programming Language :: Python :: 3
Classifier: Programming Language :: Python :: 3.8
Classifier: Programming Language :: Python :: 3.9
Classifier: Programming Language :: Python :: 3.10
Requires-Dist: dash (>=2.6.1,<3.0.0)
Requires-Dist: dash-bootstrap-components (>=1.2.1,<2.0.0)
Requires-Dist: dash-loading-spinners (>=1.0.0,<2.0.0)
Requires-Dist: gunicorn (>=20.1.0,<21.0.0)
Requires-Dist: nemosis (>=3.1.0,<4.0.0)
Requires-Dist: numpy (>=1.23.3,<2.0.0)
Requires-Dist: openpyxl (>=3.0.10,<4.0.0)
Requires-Dist: pandas (>=1.2,<2.0)
Requires-Dist: plotly (>=5.10.0,<6.0.0)
Requires-Dist: psycopg[binary] (>=3.1.4,<4.0.0)
Requires-Dist: pytest-mock (>=3.10.0,<4.0.0)
Requires-Dist: supabase (>=0.7.1,<0.8.0)
